test_scraper_pypi/__init__.py
test_scraper_pypi/cli.py
test_scraper_pypi/test_scraper_pypi.py
test_scraper_pypi-0.1.1.dist-info/AUTHORS.rst
test_scraper_pypi-0.1.1.dist-info/LICENSE
test_scraper_pypi-0.1.1.dist-info/METADATA
test_scraper_pypi-0.1.1.dist-info/WHEEL
test_scraper_pypi-0.1.1.dist-info/entry_points.txt
test_scraper_pypi-0.1.1.dist-info/top_level.txt
test_scraper_pypi-0.1.1.dist-info/RECORD
