Metadata-Version: 2.1
Name: test-scraper-pypi
Version: 0.1.1
Summary: Testing scraper package as pip package
Home-page: https://github.com/kishore-s-15/test_scraper_pypi
Author: Kishore Sampath
Author-email: skishore2602.dev@gmail.com
License: MIT license
Keywords: test_scraper_pypi
Platform: UNKNOWN
Classifier: Development Status :: 2 - Pre-Alpha
Classifier: Intended Audience :: Developers
Classifier: License :: OSI Approved :: MIT License
Classifier: Natural Language :: English
Classifier: Programming Language :: Python :: 3
Classifier: Programming Language :: Python :: 3.6
Classifier: Programming Language :: Python :: 3.7
Classifier: Programming Language :: Python :: 3.8
Requires-Python: >=3.6
Requires-Dist: Click (>=7.0)
